nestedtext.py
py_nestedtext-0.0.4.data/scripts/nt-cli
py_nestedtext-0.0.4.dist-info/LICENSE
py_nestedtext-0.0.4.dist-info/METADATA
py_nestedtext-0.0.4.dist-info/WHEEL
py_nestedtext-0.0.4.dist-info/top_level.txt
py_nestedtext-0.0.4.dist-info/RECORD
