Metadata-Version: 2.1
Name: py-nestedtext
Version: 0.0.4
Summary: Minimal implementation of NestedText data format
Home-page: UNKNOWN
Author: Lewis Gaul
Author-email: lewis.gaul@gmail.com
License: MIT
Keywords: data
Platform: UNKNOWN
Classifier: Development Status :: 2 - Pre-Alpha
Classifier: Intended Audience :: Developers
Classifier: License :: OSI Approved :: MIT License
Classifier: Natural Language :: English
Classifier: Operating System :: OS Independent
Classifier: Programming Language :: Python :: 3
Classifier: Programming Language :: Python :: 3.6
Classifier: Programming Language :: Python :: 3.7
Classifier: Programming Language :: Python :: 3.8
Classifier: Programming Language :: Python :: 3.9
Classifier: Topic :: Text Processing :: Markup
Classifier: Topic :: Utilities
Requires-Python: >=3.6
